README.md
nester.py
setup.py
example_pkg_hqx_nester.egg-info/PKG-INFO
example_pkg_hqx_nester.egg-info/SOURCES.txt
example_pkg_hqx_nester.egg-info/dependency_links.txt
example_pkg_hqx_nester.egg-info/top_level.txt