Metadata-Version: 2.1
Name: example-pkg-hqx-nester
Version: 0.0.1
Summary: nester
Home-page: https://github.com/pypa/sampleproject
Author: hqx
Author-email: 18062093789@163.com
License: UNKNOWN
Platform: UNKNOWN
Classifier: Programming Language :: Python :: 3
Classifier: License :: OSI Approved :: MIT License
Classifier: Operating System :: OS Independent
Requires-Python: >=3.6
